capslock/__init__.py
capslock/decorators.py
capslock/utils.py
capslock-2.0.1.dist-info/LICENSE
capslock-2.0.1.dist-info/METADATA
capslock-2.0.1.dist-info/WHEEL
capslock-2.0.1.dist-info/top_level.txt
capslock-2.0.1.dist-info/RECORD
