Metadata-Version: 2.1
Name: capslock
Version: 2.0.1
Summary: A utility python library for writing certain tasks in python easily & elegantly.
Home-page: https://github.com/faruk-ahmad/capslock
Author: Faruk Ahmad
Author-email: faruk.csebrur@gmail.com
License: MIT
Classifier: Programming Language :: Python :: 3
Classifier: License :: OSI Approved :: MIT License
Classifier: Operating System :: OS Independent
Requires-Python: >=3.5
License-File: LICENSE
Requires-Dist: numpy
Requires-Dist: matplotlib
Requires-Dist: psutil
